text2struct/__init__.py
text2struct/_modidx.py
text2struct/core.py
text2struct-0.0.2.dist-info/LICENSE
text2struct-0.0.2.dist-info/METADATA
text2struct-0.0.2.dist-info/WHEEL
text2struct-0.0.2.dist-info/entry_points.txt
text2struct-0.0.2.dist-info/top_level.txt
text2struct-0.0.2.dist-info/RECORD
